essencia_core/__init__.py
essencia_core/db/__init__.py
essencia_core/db/deta/__init__.py
essencia_core/db/deta/base.py
essencia_core/forms/__init__.py
essencia_core/forms/base.py
essencia_core/models/__init__.py
essencia_core/models/abstract.py
essencia_core/models/assistant.py
essencia_core/models/base.py
essencia_core/models/care.py
essencia_core/models/patient.py
essencia_core/models/provider.py
essencia_core/utils/__init__.py
essencia_core/utils/base.py
essencia_core-0.1.51.dist-info/WHEEL
essencia_core-0.1.51.dist-info/METADATA
essencia_core-0.1.51.dist-info/RECORD
