Metadata-Version: 2.1
Name: essencia-core
Version: 0.1.51
Summary: 
Author: arantesdv
Author-email: arantesdv@me.com
Requires-Python: >=3.7,<4.0
Classifier: Programming Language :: Python :: 3
Classifier: Programming Language :: Python :: 3.7
Classifier: Programming Language :: Python :: 3.8
Classifier: Programming Language :: Python :: 3.9
Requires-Dist: Jinja2 (>=3.0.1,<4.0.0)
Requires-Dist: MarkupSafe (>=2.0.1,<3.0.0)
Requires-Dist: bootstrap4 (>=0.1.0,<0.2.0)
Requires-Dist: deta (>=0.8,<0.9)
Requires-Dist: starlette (>=0.14.2,<0.15.0)
Requires-Dist: typesystem (>=0.2.4,<0.3.0)
Requires-Dist: uvicorn (>=0.14.0,<0.15.0)
